llm_memory.py
llm_user_memory-0.1.1.dist-info/licenses/LICENSE
llm_user_memory-0.1.1.dist-info/METADATA
llm_user_memory-0.1.1.dist-info/WHEEL
llm_user_memory-0.1.1.dist-info/entry_points.txt
llm_user_memory-0.1.1.dist-info/top_level.txt
llm_user_memory-0.1.1.dist-info/RECORD
