Metadata-Version: 2.4
Name: llm-user-memory
Version: 0.1.1
Summary: Transparent memory system for LLM
Author-email: Rodrigo Serrano <jrodrigosm@gmail.com>
License-Expression: Apache-2.0
Project-URL: Homepage, https://github.com/jrodrigosm/llm-user-memory
Project-URL: Repository, https://github.com/jrodrigosm/llm-user-memory
Project-URL: Issues, https://github.com/jrodrigosm/llm-user-memory/issues
Keywords: llm,memory,ai,chatbot,plugin
Classifier: Development Status :: 4 - Beta
Classifier: Intended Audience :: Developers
Classifier: Programming Language :: Python :: 3
Classifier: Programming Language :: Python :: 3.8
Classifier: Programming Language :: Python :: 3.9
Classifier: Programming Language :: Python :: 3.10
Classifier: Programming Language :: Python :: 3.11
Classifier: Programming Language :: Python :: 3.12
Classifier: Topic :: Software Development :: Libraries :: Python Modules
Classifier: Topic :: Scientific/Engineering :: Artificial Intelligence
Requires-Python: >=3.8
License-File: LICENSE
Requires-Dist: llm>=0.26
Provides-Extra: test
Requires-Dist: pytest>=7.0.0; extra == "test"
Requires-Dist: pytest-cov>=4.0.0; extra == "test"
Requires-Dist: pytest-mock>=3.10.0; extra == "test"
Requires-Dist: pytest-asyncio>=0.21.0; extra == "test"
Requires-Dist: pytest-xdist>=3.0.0; extra == "test"
Requires-Dist: pytest-click>=1.1.0; extra == "test"
Requires-Dist: coverage>=7.0.0; extra == "test"
Requires-Dist: responses>=0.23.0; extra == "test"
Provides-Extra: dev
Requires-Dist: black>=23.0.0; extra == "dev"
Requires-Dist: flake8>=6.0.0; extra == "dev"
Requires-Dist: mypy>=1.0.0; extra == "dev"
Requires-Dist: pre-commit>=3.0.0; extra == "dev"
Dynamic: license-file
